.gitignore
.travis.yml
CHANGES.rst
MANIFEST.in
README.rst
build-i18n.sh
buildout.cfg
setup.py
collective/__init__.py
collective.geolocationbehavior.egg-info/PKG-INFO
collective.geolocationbehavior.egg-info/SOURCES.txt
collective.geolocationbehavior.egg-info/dependency_links.txt
collective.geolocationbehavior.egg-info/entry_points.txt
collective.geolocationbehavior.egg-info/namespace_packages.txt
collective.geolocationbehavior.egg-info/not-zip-safe
collective.geolocationbehavior.egg-info/requires.txt
collective.geolocationbehavior.egg-info/top_level.txt
collective/geolocationbehavior/__init__.py
collective/geolocationbehavior/configure.zcml
collective/geolocationbehavior/geolocation.py
collective/geolocationbehavior/indexer.py
collective/geolocationbehavior/interfaces.py
collective/geolocationbehavior/locales/collective.geolocationbehavior.pot
collective/geolocationbehavior/locales/de/LC_MESSAGES/collective.geolocationbehavior.po
collective/geolocationbehavior/locales/fr/LC_MESSAGES/collective.geolocationbehavior.po
collective/geolocationbehavior/locales/it/LC_MESSAGES/collective.geolocationbehavior.po
collective/geolocationbehavior/profiles/default/catalog.xml
collective/geolocationbehavior/profiles/default/metadata.xml
collective/geolocationbehavior/profiles/uninstall/metadata.xml
collective/geolocationbehavior/upgrades/__init__.py
collective/geolocationbehavior/upgrades/configure.zcml
docs/INSTALL.txt
docs/LICENSE.GPL
docs/LICENSE.txt